oompa/__init__.py
oompa/oompa.py
oompa/ansible_clients/__init__.py
oompa/ansible_clients/ansible_runner.py
oompa/ansible_clients/roles_installer.py
oompa/docker_clients/__init__.py
oompa/docker_clients/container_manager.py
oompa/file_parser/__init__.py
oompa/file_parser/file_parser.py
oompa/utils/__init__.py
oompa/utils/keystore.py
oompa/utils/oompa-bootstrap.sh.tar
oompa-0.0.3.dist-info/LICENSE
oompa-0.0.3.dist-info/METADATA
oompa-0.0.3.dist-info/WHEEL
oompa-0.0.3.dist-info/entry_points.txt
oompa-0.0.3.dist-info/top_level.txt
oompa-0.0.3.dist-info/RECORD
