Metadata-Version: 2.1
Name: oompa
Version: 0.0.3
Summary: A tool to build Docker images with an easy to read configuration
Home-page: https://gitlab.com/davidbuzinski/oompa
Author: David Buzinski
Author-email: davidbuzinski@gmail.com
License: UNKNOWN
Project-URL: Source Code, https://gitlab.com/davidbuzinski/oompa
Project-URL: Bug Tracker, https://gitlab.com/davidbuzinski/oompa/-/issues
Platform: UNKNOWN
Classifier: Development Status :: 3 - Alpha
Classifier: Environment :: Console
Classifier: Intended Audience :: Developers
Classifier: Intended Audience :: Information Technology
Classifier: Operating System :: OS Independent
Classifier: Programming Language :: Python
Classifier: Programming Language :: Python :: 3
Classifier: Programming Language :: Python :: 3.6
Classifier: Programming Language :: Python :: 3.7
Classifier: Programming Language :: Python :: 3.8
Classifier: Programming Language :: Python :: 3.9
Classifier: Programming Language :: Python :: 3.10
Classifier: Topic :: Software Development
Classifier: Topic :: System :: Installation/Setup
Classifier: Topic :: System :: Systems Administration
Classifier: Topic :: Utilities
Classifier: License :: OSI Approved :: MIT License
Requires-Python: >=3.6
License-File: LICENSE
Requires-Dist: ansible (>=4.10.0)
Requires-Dist: ansible-runner (>=2.1.3)
Requires-Dist: dhall (>=0.1.9)
Requires-Dist: docker (>=5.0.3)
